{"cameraMode":{"drawMode":0,"name":"Shaded","section":"Shading Mode"},"sceneLighting":false,"audioPlay":false,"sceneViewState":{"m_AlwaysRefresh":false,"showFog":true,"showSkybox":false,"showFlares":true,"showImageEffects":true,"showParticleSystems":true,"showVisualEffectGraphs":true,"m_FxEnabled":true},"in2DMode":false,"pivot":{"x":1.698344111442566,"y":6.937635898590088,"z":8.242961883544922},"rotation":{"x":0.12140662223100662,"y":0.3878386914730072,"z":-0.0516173429787159,"w":0.9122454524040222},"size":1.7862553596496583,"orthographic":false}